mirdeepsquared/__init__.py
mirdeepsquared/best-hyperparameters.yaml
mirdeepsquared/common.py
mirdeepsquared/correct_invalid_labels.py
mirdeepsquared/default-hyperparameters.yaml
mirdeepsquared/density_map_model.py
mirdeepsquared/estimation_model.py
mirdeepsquared/extract_features.py
mirdeepsquared/mirgene_db_filter.py
mirdeepsquared/mod_html.py
mirdeepsquared/model.py
mirdeepsquared/model_weights.yaml
mirdeepsquared/motifs_bayes_model.py
mirdeepsquared/numerical_model.py
mirdeepsquared/predict.py
mirdeepsquared/predict_cmd.py
mirdeepsquared/structure_model.py
mirdeepsquared/train.py
mirdeepsquared/train_ensemble.py
mirdeepsquared/models/DensityMapModel_with_location_of_mature_star_and_hairpin.keras
mirdeepsquared/models/EstimationModel_model.pkl
mirdeepsquared/models/MotifModel_motifs.pkl
mirdeepsquared/models/NumericalModel_simple.keras
mirdeepsquared/models/StructureModel_simple.keras
mirdeepsquared-0.7.0.dist-info/LICENSE.txt
mirdeepsquared-0.7.0.dist-info/METADATA
mirdeepsquared-0.7.0.dist-info/WHEEL
mirdeepsquared-0.7.0.dist-info/entry_points.txt
mirdeepsquared-0.7.0.dist-info/top_level.txt
mirdeepsquared-0.7.0.dist-info/RECORD
