Metadata-Version: 2.1
Name: mirdeepsquared
Version: 0.7.0
Summary: Filters out false positives from the novel section of the output from miRDeep2
Home-page: https://github.com/jontejj/mirdeepsquared
Author: Jonatan Jönsson
Author-email: jontejj@gmail.com
Project-URL: Bug Reports, https://github.com/jontejj/mirdeepsquared/issues
Project-URL: Say Thanks!, https://saythanks.io/to/jontejj
Project-URL: Source, https://github.com/jontejj/mirdeepsquared/
Keywords: miRDeep2,miRNA,deeplearning
Classifier: Development Status :: 3 - Alpha
Classifier: Intended Audience :: Science/Research
Classifier: Topic :: Scientific/Engineering :: Artificial Intelligence
Classifier: License :: OSI Approved :: MIT License
Classifier: Programming Language :: Python :: 3
Classifier: Programming Language :: Python :: 3.9
Classifier: Programming Language :: Python :: 3 :: Only
Requires-Python: >=3.9, <4
License-File: LICENSE.txt
Requires-Dist: tensorflow<2.16,>=2.15
Requires-Dist: tensorflow-metal>=1.0; platform_system == "Darwin" and platform_machine == "arm64"
Requires-Dist: numpy~=1.24.3
Requires-Dist: screed
Requires-Dist: pandas
Requires-Dist: scikit-learn
Requires-Dist: pyyaml
Requires-Dist: beautifulsoup4
Provides-Extra: test
Requires-Dist: pytest; extra == "test"
Requires-Dist: coverage; extra == "test"
